[
{	"atributos": {		"fechaCreacion":"2016-03-09",		"fechaHoraCreacion":"2016-03-09 10:23:30"	},	"informado": {		"situacion":"contribuyente",		"ruc":"80033703",		"dv":"4",		"tipoIdentificacion":"",		"identificacion":"",		"nombre":"GASPARINI INFORMATICA S.R.L.",		"domicilio":"Avda. La Victoria 1951",		"direccion":"",		"correoElectronico":"",		"pais":"",		"telefono":""	},	"transaccion": {		"condicionCompra":"CONTADO",		"cuotas":0,		"tipoComprobante":1,		"numeroComprobanteVenta":"001-001-5011",		"fecha":"2016-03-09",		"numeroTimbrado":"68613677"	},	"detalle": [		{			"cantidad":1.00,			"tasaAplica":"10",			"precioUnitario":1000000.00,			"descripcion":"MERCADERIA GRAVADO 10%"		}	],	"retencion": {		"fecha":"2016-03-09",		"moneda":"PYG",		"retencionRenta":false,		"conceptoRenta":"",		"retencionIva":true,		"conceptoIva":"IVA.1",		"rentaPorcentaje":0,		"rentaCabezasBase":0,		"rentaCabezasCantidad":0,		"rentaToneladasBase":0,		"rentaToneladasCantidad":0,		"ivaPorcentaje5":30.000000,		"ivaPorcentaje10":30.000000	}}
]
